{"trial_id": "0015", "hyperparameters": {"space": [{"class_name": "Choice", "config": {"name": "activation", "default": "relu", "conditions": [], "values": ["relu", "tanh"], "ordered": false}}, {"class_name": "Int", "config": {"name": "layer_1", "default": null, "conditions": [], "min_value": 32, "max_value": 512, "step": 32, "sampling": "linear"}}, {"class_name": "Choice", "config": {"name": "learning_rate", "default": 0.01, "conditions": [], "values": [0.01, 0.001, 0.0001], "ordered": true}}], "values": {"activation": "tanh", "layer_1": 416, "learning_rate": 0.001, "tuner/epochs": 4, "tuner/initial_epoch": 2, "tuner/bracket": 2, "tuner/round": 1, "tuner/trial_id": "0002"}}, "metrics": {"metrics": {"accuracy": {"direction": "max", "observations": [{"value": [0.9975894093513489], "step": 0}]}, "loss": {"direction": "min", "observations": [{"value": [0.010183615610003471], "step": 0}]}}}, "score": 0.9975894093513489, "best_step": 0, "status": "COMPLETED", "message": null}